django_countries_hdx/__init__.py
django_countries_hdx/hdx_plus_m49.csv
django_countries_hdx-2.1.1.dist-info/licenses/LICENSE
django_countries_hdx-2.1.1.dist-info/METADATA
django_countries_hdx-2.1.1.dist-info/WHEEL
django_countries_hdx-2.1.1.dist-info/entry_points.txt
django_countries_hdx-2.1.1.dist-info/top_level.txt
django_countries_hdx-2.1.1.dist-info/RECORD
