Metadata-Version: 2.4
Name: django-countries-hdx
Version: 2.1.1
Summary: Adds extra M49 data to django-countries using hdx-python-country.
Author: Internet Society
License: MIT
Project-URL: Homepage, https://github.com/InternetSociety/django-countries-hdx
Project-URL: Changelog, https://github.com/InternetSociety/django-countries-hdx/releases
Project-URL: Issues, https://github.com/InternetSociety/django-countries-hdx/issues
Project-URL: CI, https://github.com/InternetSociety/django-countries-hdx/actions
Classifier: License :: OSI Approved :: MIT License
Classifier: Natural Language :: English
Classifier: Operating System :: OS Independent
Classifier: Programming Language :: Python
Classifier: Framework :: Django
Requires-Python: >=3.10
License-File: LICENSE
Requires-Dist: django>4.2
Requires-Dist: django-countries>7.6.0
Requires-Dist: hdx-python-country~=3.8.5
Requires-Dist: hdx-python-utilities~=3.9
Provides-Extra: test
Requires-Dist: pytest; extra == "test"
Requires-Dist: django_countries; extra == "test"
Requires-Dist: pandas; extra == "test"
Dynamic: license-file
